fps_debut_package/__init__.py
fps_debut_package/functions.py
fps_debut_package/greet.py
fps_debut_package-0.0.1.dist-info/LICENSE.txt
fps_debut_package-0.0.1.dist-info/METADATA
fps_debut_package-0.0.1.dist-info/WHEEL
fps_debut_package-0.0.1.dist-info/top_level.txt
fps_debut_package-0.0.1.dist-info/RECORD
