Metadata-Version: 2.1
Name: fps-debut-package
Version: 0.0.1
Summary: First Package
Home-page: https://github.com/0xfps/first-python-package
Author: fps
Author-email: anthony.nnaemeka.umeh@gmail.com
License: MIT License        
Project-URL: fps-package, https://github.com/0xfps/first-python-package
Project-URL: 0xfps, https://github.com/0xfps
Classifier: Programming Language :: Python :: 3
Classifier: Operating System :: OS Independent
Classifier: License :: OSI Approved :: MIT License
Requires-Python: >=3.6
License-File: LICENSE.txt
